test/__init__.py
test/test_accessory_data.py
test/test_action_required_data.py
test/test_action_taken_data.py
test/test_active_inactive_date_overrides_data.py
test/test_additional_dull_grading_data.py
test/test_afe_cost_data.py
test/test_afe_data.py
test/test_agreement_data.py
test/test_agreement_date_data.py
test/test_agreement_link_data.py
test/test_anchor_data.py
test/test_annular_fluid_data.py
test/test_approval_process_data.py
test/test_approve_data.py
test/test_attachment_data.py
test/test_attribute_data.py
test/test_bad_actor_moc_data.py
test/test_bit_nozzle_data.py
test/test_bop_data.py
test/test_bottom_hole_core_data.py
test/test_carter_location_data.py
test/test_casing_comp_status_history_data.py
test/test_casing_component_data.py
test/test_casing_strings_data.py
test/test_cause_analysis_data.py
test/test_cement_data.py
test/test_cement_fluid_additive_data.py
test/test_cement_fluid_data.py
test/test_cement_fluid_viscometer_reading_data.py
test/test_cement_stage_data.py
test/test_centrifuge_cyclone_check_data.py
test/test_centrifuge_cyclone_data.py
test/test_comments_data.py
test/test_completion_alias_history_data.py
test/test_completion_data.py
test/test_completion_links_data.py
test/test_completion_status_data.py
test/test_congressional_location_data.py
test/test_continuous_chemical_injection_data.py
test/test_control_line_detail_data.py
test/test_crew_training_data.py
test/test_criteria_data.py
test/test_daily_operation_data.py
test/test_daily_pressure_data.py
test/test_data_obligation_data.py
test/test_date_override_data.py
test/test_default_api.py
test/test_deliverable_data.py
test/test_detailed_analysis_data.py
test/test_deviation_survey_data.py
test/test_discharge_data.py
test/test_dls_location_data.py
test/test_down_time_data.py
test/test_drill_bit_data.py
test/test_drill_string_component_data.py
test/test_drill_string_data.py
test/test_drilling_parameter_data.py
test/test_drilling_parameter_program_data.py
test/test_dynamometer_test_data.py
wellview_sdk_api-1.0.13.dist-info/METADATA
wellview_sdk_api-1.0.13.dist-info/WHEEL
wellview_sdk_api-1.0.13.dist-info/top_level.txt
wellview_sdk_api-1.0.13.dist-info/RECORD
