Metadata-Version: 2.1
Name: wellview-sdk-api
Version: 1.0.13
Summary: WellViewSDKAPI
Home-page: 
Author-email: 
Keywords: Swagger,WellViewSDKAPI
Requires-Dist: urllib3 (>=1.15)
Requires-Dist: six (>=1.10)
Requires-Dist: certifi
Requires-Dist: python-dateutil
